metalmetrics/__init__.py
metalmetrics/__version__.py
metalmetrics/main.py
metalmetrics/cmd/__init__.py
metalmetrics/cmd/argument.py
metalmetrics/cmd/banner.py
metalmetrics/config/__init__.py
metalmetrics/config/config.py
metalmetrics/config/config.yml
metalmetrics/flow/__init__.py
metalmetrics/flow/flow.py
metalmetrics/flow/flow_pb2.py
metalmetrics/flow/flow_pb2_grpc.py
metalmetrics/logger/__init__.py
metalmetrics/logger/logger.py
metalmetrics/metrics/__init__.py
metalmetrics/metrics/abstract.py
metalmetrics/metrics/bare.py
metalmetrics/metrics/metrics.py
metalmetrics/printer/__init__.py
metalmetrics/printer/printer.py
metalmetrics/proto/__init__.py
metalmetrics/proto/proto.py
metalmetrics/queue/__init__.py
metalmetrics/queue/queue.py
metalmetrics-7.1.1.dist-info/LICENSE
metalmetrics-7.1.1.dist-info/METADATA
metalmetrics-7.1.1.dist-info/WHEEL
metalmetrics-7.1.1.dist-info/entry_points.txt
metalmetrics-7.1.1.dist-info/top_level.txt
metalmetrics-7.1.1.dist-info/RECORD
