Metadata-Version: 2.1
Name: metalmetrics
Version: 7.1.1
Summary: Metal Metrics
Home-page: https://github.com/craftslab/metalmetrics
Author: Jia Jia
Author-email: angersax@sina.com
License: Apache-2.0
Download-URL: https://github.com/craftslab/metalmetrics/archive/v7.1.1.tar.gz
Keywords: metal,metrics
Platform: UNKNOWN
Classifier: Development Status :: 3 - Alpha
Classifier: Intended Audience :: Developers
Classifier: Programming Language :: Python :: 3
Classifier: License :: OSI Approved :: Apache Software License
Classifier: Operating System :: OS Independent
License-File: LICENSE
Requires-Dist: black
Requires-Dist: colorama
Requires-Dist: coverage
Requires-Dist: coveralls
Requires-Dist: flake8
Requires-Dist: grpcio
Requires-Dist: grpcio-tools
Requires-Dist: hypothesis
Requires-Dist: mypy
Requires-Dist: openpyxl
Requires-Dist: pre-commit
Requires-Dist: psutil
Requires-Dist: psycopg2-binary
Requires-Dist: pyinstaller
Requires-Dist: pytest
Requires-Dist: pyyaml
Requires-Dist: setuptools
Requires-Dist: twine
Requires-Dist: wheel
